.gitignore
MANIFEST.in
README.rst
bootstrap.py
buildout.cfg
setup.py
collective/__init__.py
collective.js.formalize.egg-info/PKG-INFO
collective.js.formalize.egg-info/SOURCES.txt
collective.js.formalize.egg-info/dependency_links.txt
collective.js.formalize.egg-info/entry_points.txt
collective.js.formalize.egg-info/namespace_packages.txt
collective.js.formalize.egg-info/not-zip-safe
collective.js.formalize.egg-info/requires.txt
collective.js.formalize.egg-info/top_level.txt
collective/js/__init__.py
collective/js/formalize/__init__.py
collective/js/formalize/configure.zcml
collective/js/formalize/interfaces.py
collective/js/formalize/upgrades.py
collective/js/formalize/profiles/default/cssregistry.xml
collective/js/formalize/profiles/default/jsregistry.xml
collective/js/formalize/profiles/default/metadata.xml
collective/js/formalize/resources/css/_formalize.sass
collective/js/formalize/resources/css/demo.css
collective/js/formalize/resources/css/formalize.css
collective/js/formalize/resources/css/reset.css
collective/js/formalize/resources/css/text.css
collective/js/formalize/resources/images/button.png
collective/js/formalize/resources/images/select_arrow.gif
collective/js/formalize/resources/js/jquery.formalize.js
collective/js/formalize/resources/js/jquery.formalize.min.js
docs/HISTORY.txt