Metadata-Version: 1.0
Name: collective.js.formalize
Version: 1.1
Summary: Register Formalize into Plone resource registries
Home-page: https://github.com/collective/collective.js.formalize
Author: JeanMichel FRANCOIS aka toutpt
Author-email: toutpt@gmail.com
License: GPL
Platform: UNKNOWN
Classifier: Programming Language :: Python
